{
  "schema_version": 1,
  "project_slug": "enigmatic-skies",
  "sources": {
    "ftbquests": {
      "converter_type": "ftb-quests-lang-splitter",
      "paratranz_files": [
        "ftbquests/chapter_group.json",
        "ftbquests/chapters/0EFE9E753A92388D.json",
        "ftbquests/chapters/25ADADD36B4FDE05.json",
        "ftbquests/chapters/402AE6264B81A84B.json",
        "ftbquests/chapters/47870879D8E3742D.json",
        "ftbquests/chapters/777EE0C4949DFE12.json",
        "ftbquests/chapters/7F17CDF8564DCC49.json",
        "ftbquests/chapters/acclimation.json",
        "ftbquests/chapters/ars_nouveau.json",
        "ftbquests/chapters/blazing.json",
        "ftbquests/chapters/cascading.json",
        "ftbquests/chapters/equipment.json",
        "ftbquests/chapters/flashing.json",
        "ftbquests/chapters/flourishing.json",
        "ftbquests/chapters/it_takes_a_village.json",
        "ftbquests/chapters/malum.json",
        "ftbquests/chapters/natures_aura.json",
        "ftbquests/chapters/pneumaticcraft.json",
        "ftbquests/chapters/power_generation.json",
        "ftbquests/chapters/replication.json",
        "ftbquests/chapters/the_beginning.json",
        "ftbquests/chapters/vexing.json",
        "ftbquests/file.json",
        "ftbquests/reward_table.json",
        "ftbquests/unassigned/chapter.json",
        "ftbquests/unassigned/quest.json",
        "ftbquests/unassigned/reward.json",
        "ftbquests/unassigned/task.json"
      ],
      "key_meta_files": [
        "ftbquests/chapter_group.json",
        "ftbquests/chapters/0EFE9E753A92388D.json",
        "ftbquests/chapters/25ADADD36B4FDE05.json",
        "ftbquests/chapters/402AE6264B81A84B.json",
        "ftbquests/chapters/47870879D8E3742D.json",
        "ftbquests/chapters/777EE0C4949DFE12.json",
        "ftbquests/chapters/7F17CDF8564DCC49.json",
        "ftbquests/chapters/acclimation.json",
        "ftbquests/chapters/ars_nouveau.json",
        "ftbquests/chapters/blazing.json",
        "ftbquests/chapters/cascading.json",
        "ftbquests/chapters/equipment.json",
        "ftbquests/chapters/flashing.json",
        "ftbquests/chapters/flourishing.json",
        "ftbquests/chapters/it_takes_a_village.json",
        "ftbquests/chapters/malum.json",
        "ftbquests/chapters/natures_aura.json",
        "ftbquests/chapters/pneumaticcraft.json",
        "ftbquests/chapters/power_generation.json",
        "ftbquests/chapters/replication.json",
        "ftbquests/chapters/the_beginning.json",
        "ftbquests/chapters/vexing.json",
        "ftbquests/file.json",
        "ftbquests/reward_table.json",
        "ftbquests/unassigned/chapter.json",
        "ftbquests/unassigned/quest.json",
        "ftbquests/unassigned/reward.json",
        "ftbquests/unassigned/task.json"
      ]
    }
  }
}
